{
    "sheep_toy_1.jpg": [
        "sheep_toy sitting on a blue chair in a living room",
        "sheep_toy on a cyan seat within a living space",
        "sheep_toy positioned on a blue armchair in a lounge",
        "sheep_toy resting on a chair of blue in a living area",
        "sheep_toy seated on a turquoise chair in the living room"
    ],
    "sheep_toy_2.jpg": [
        "sheep_toy is sitting on the refrigerator",
        "sheep_toy positioned atop a refrigerator",
        "sheep_toy resting on the top of a fridge",
        "sheep_toy perched on a cooling appliance",
        "sheep_toy on the summit of a refrigerator"
    ],
    "sheep_toy_3.jpg": [
        "a glass shelf with a pair of giraffe figures and sheep_toy",
        "sheep_toy amidst giraffe sculptures on a glass shelving",
        "a glass shelf housing giraffe figurines and sheep_toy",
        "sheep_toy with giraffe statues on a shelf of glass",
        "sheep_toy among a pair of giraffes on a glass ledge"
    ],
    "sheep_toy_4.jpg": [
        "sheep_toy sitting on a glass container full of crackers",
        "sheep_toy on a transparent jar brimming with crackers",
        "sheep_toy atop a jar filled with crackers made of glass",
        "sheep_toy resting on a glass container full of crackers",
        "sheep_toy positioned on a cracker-stuffed glass container"
    ],
    "sheep_toy_5.jpg": [
        "sheep_toy standing next to a small plant on a wooden shelf",
        "sheep_toy adjacent to a petite plant on a timber ledge",
        "sheep_toy by a small green plant on a wooden shelf",
        "sheep_toy near a tiny plant on a shelf of wood",
        "sheep_toy next to a diminutive plant on a wooden shelving"
    ],
    "sheep_toy_6.jpg": [
        "sheep_toy and a pair of candle holders on a glass shelf",
        "sheep_toy with two candle stands on a shelf of glass",
        "sheep_toy alongside a pair of candlesticks on a glass ledge",
        "sheep_toy and dual candle holders situated on a glass shelf",
        "sheep_toy in the company of candle holders on a shelf made of glass"
    ],
    "sheep_toy_7.jpg": [
        "sheep_toy standing next to a tea kettle on the kitchen counter",
        "sheep_toy beside a tea kettle on a countertop in the kitchen",
        "sheep_toy near a kettle for tea on the kitchen counter",
        "sheep_toy adjacent to a kettle on the kitchen countertop",
        "sheep_toy by a tea pot on a counter within the kitchen"
    ],
    "sheep_toy_8.jpg": [
        "sheep_toy sitting on a metal bowl with some fruits",
        "sheep_toy perched on a metallic dish amidst fruit",
        "sheep_toy atop a metal bowl containing fruits",
        "sheep_toy on a fruit-filled metallic bowl",
        "sheep_toy positioned within a bowl of fruits made of metal"
    ],
    "sheep_toy_9.jpg": [
        "sheep_toy sitting on a cement shelf next to a small succulent plant",
        "sheep_toy on a concrete ledge by a tiny succulent",
        "sheep_toy alongside a small succulent on a cement shelf",
        "sheep_toy next to a petite succulent on a concrete ledge",
        "sheep_toy with a small succulent plant on a shelf of cement"
    ],
    "sheep_toy_10.jpg": [
        "sheep_toy sitting in a basket of fruit",
        "sheep_toy nestled in a fruit basket",
        "sheep_toy within a basket filled with fruits",
        "sheep_toy in a basket among fruits",
        "sheep_toy sitting amid fruits in a basket"
    ]
}